<?xml version="1.0" encoding="UTF-8"?><database>
    <element db_object_id="3f5ed37e9741a110daa03df6f053af7e" label="mhbkj,hn" max_length="40" name="x_snc_vj_new_app_0_mhbkj_hn" type="collection">
        <element attributes="edge_encryption_enabled=true" label="Active" max_length="40" name="active" type="string"/>
        <element attributes="edge_encryption_enabled=true" label="Created" max_length="40" name="created" type="glide_date_time"/>
        <element attributes="edge_encryption_enabled=true" label="Email" max_length="40" name="email" type="string"/>
        <element attributes="edge_encryption_enabled=true" label="Locked out" max_length="40" name="locked_out" type="string"/>
        <element attributes="edge_encryption_enabled=true" label="Name" max_length="40" name="name" type="string"/>
        <element attributes="edge_encryption_enabled=true" label="Updated" max_length="40" name="updated" type="glide_date_time"/>
        <element attributes="edge_encryption_enabled=true" label="User ID" max_length="40" name="user_id" type="string"/>
        <element attributes="edge_encryption_enabled=true" label="User type" max_length="40" name="user_type" type="string"/>
    </element>
</database>
